quotes_library/__init__.py
quotes_library/db.sqlite3
quotes_library/main.py
quotes_library/utils.py
quotes_library-1.0.1.dist-info/licenses/LICENSE
quotes_library-1.0.1.dist-info/METADATA
quotes_library-1.0.1.dist-info/WHEEL
quotes_library-1.0.1.dist-info/top_level.txt
quotes_library-1.0.1.dist-info/RECORD
