Metadata-Version: 2.4
Name: quotes_library
Version: 1.0.1
Summary: This python library generates quotes
Author-email: Anthony Emmanuel <mymi14s@hotmail.com>
License: MIT
Project-URL: Homepage, https://github.com/mymi14s/quotes_library
Project-URL: Issues, https://github.com/mymi14s/quotes_library/issues
Classifier: Programming Language :: Python :: 3
Classifier: Programming Language :: Python :: 3.11
Classifier: Programming Language :: Python :: 3.12
Classifier: Programming Language :: Python :: 3.13
Classifier: Programming Language :: Python :: 3.14
Classifier: License :: OSI Approved :: MIT License
Classifier: Operating System :: OS Independent
Requires-Python: >=3.11
License-File: LICENSE
Requires-Dist: requests
Dynamic: license-file
